msurrogate/__init__.py
msurrogate/auto_version.py
msurrogate/meta_app.py
msurrogate/meta_daemon.py
msurrogate/meta_proxy.py
msurrogate/ping_test.py
msurrogate/subproc_server.py
msurrogate/version.py
msurrogate/+msurrogate/PySurrogate.m
msurrogate/+msurrogate/cell2py.m
msurrogate/+msurrogate/collectargs.m
msurrogate/+msurrogate/dict2map.m
msurrogate/+msurrogate/dict2struct.m
msurrogate/+msurrogate/getfielddefault.m
msurrogate/+msurrogate/map2dict.m
msurrogate/+msurrogate/mat2np.m
msurrogate/+msurrogate/mat2py.m
msurrogate/+msurrogate/py2mat.m
msurrogate/+msurrogate/pyapply.m
msurrogate/+msurrogate/pyrowrap.m
msurrogate/+msurrogate/pywrap.m
msurrogate/+msurrogate/struct2py.m
msurrogate/+msurrogate/tup2mat.m
msurrogate-0.9.0rc3.dist-info/DESCRIPTION.rst
msurrogate-0.9.0rc3.dist-info/METADATA
msurrogate-0.9.0rc3.dist-info/RECORD
msurrogate-0.9.0rc3.dist-info/WHEEL
msurrogate-0.9.0rc3.dist-info/metadata.json
msurrogate-0.9.0rc3.dist-info/top_level.txt
