Metadata-Version: 2.0
Name: msurrogate
Version: 0.9.0rc3
Summary: Interface With an out-of-process (possibly remote) python instance from Matlab
Home-page: https://github.com/mccullerlp/msurrogate
Author: Lee McCuller
Author-email: Lee.McCuller@gmail.com
License: Apache v2
Keywords: Matlab,IPC,Pyro4
Platform: UNKNOWN
Classifier: Development Status :: 4 - Beta
Classifier: Intended Audience :: Developers
Classifier: Topic :: Scientific/Engineering
Classifier: License :: OSI Approved :: Apache Software License
Classifier: Operating System :: OS Independent
Classifier: Programming Language :: Python
Classifier: Programming Language :: Python :: 2
Classifier: Programming Language :: Python :: 2.7
Classifier: Programming Language :: Python :: 3
Classifier: Programming Language :: Python :: 3.4
Classifier: Programming Language :: Python :: 3.5
Classifier: Programming Language :: Python :: 3.6
Requires-Dist: numpy
Requires-Dist: Pyro4
